LICENSE
MANIFEST.in
README.md
setup.py
rsharp/__init__.py
rsharp/builder.py
rsharp/icon.ico
rsharp/icon.png
rsharp/main.py
rsharp/rsxlib.py
rsharp/std.py
rsharp/tools.py
rsharp/transpiler.py
rsharp.egg-info/PKG-INFO
rsharp.egg-info/SOURCES.txt
rsharp.egg-info/dependency_links.txt
rsharp.egg-info/requires.txt
rsharp.egg-info/top_level.txt
rsharp/include/rsxbuild/init.rsxh
rsharp/include/rsxbuild/rsxbuild.py
rsharp/include/rsxf/init.rsxh
rsharp/include/rsxf/rsxf.py
rsharp/include/rsxgui/init.rsxh
rsharp/include/rsxgui/rsxgui.py
rsharp/include/rsxio/init.rsxh
rsharp/include/rsxio/rsxio.py
rsharp/include/rsxmath/init.rsxh
rsharp/include/rsxmath/rsxmath.py
rsharp/include/rsxmixer/init.rsxh
rsharp/include/rsxmixer/rsxmixer.py
rsharp/include/rsxrand/init.rsxh
rsharp/include/rsxrand/rsxrand.py
rsharp/include/rsxraylib/audio.py
rsharp/include/rsxraylib/colors.py
rsharp/include/rsxraylib/consts.rsxh
rsharp/include/rsxraylib/core.py
rsharp/include/rsxraylib/extras.py
rsharp/include/rsxraylib/globals.py
rsharp/include/rsxraylib/init.rsxh
rsharp/include/rsxraylib/models.py
rsharp/include/rsxraylib/shapes.py
rsharp/include/rsxraylib/structs.py
rsharp/include/rsxraylib/text.py
rsharp/include/rsxraylib/textures.py
rsharp/include/rsxstd/init.rsxh
rsharp/include/rsxstd/rsxstd.py
rsharp/include/rsxstr/init.rsxh
rsharp/include/rsxstr/rsxstr.py
rsharp/include/rsxsys/init.rsxh
rsharp/include/rsxsys/rsxsys.py
rsharp/include/rsxterm/init.rsxh
rsharp/include/rsxterm/rsxterm.py
rsharp/include/rsxtime/init.rsxh
rsharp/include/rsxtime/rsxtime.py