Metadata-Version: 2.1
Name: rsharp
Version: 0.0.7
Summary: An interpreted statically typed multi paradigm general purpose programming language designed for cross platform applications.
Home-page: https://github.com/Aermoss/RSharp
Author: Yusuf Rencber
Author-email: yusufrencber546@gmail.com
License: MIT
Platform: UNKNOWN
License-File: LICENSE
